{
  "category": "Quality",
  "code": "Q4B",
  "title": "薬局方テキストのICH地域における相互利用",
  "step": "Step 5",
  "filename": "000156021.pdf",
  "content_summary": "各都道府県衛生主管部（局）長  殿 \n\n薬 食 審 査 発 第 052 6001 号 \n平 成 2 1 年 ５ 月 2 6 日 \n\n厚生労働省医薬食品局審査管理課長       \n\n薬局方テキストを ICH 地域において相互利用するための評価及び勧告 \nに関するガイドライン（ICHQ4B ガイドライン）について \n\n近年、優れた新医薬品の地球規模での研究開発の促進と、患者への迅速な提供を図\n\nるため、承認審査資料の国際的ハーモナイゼーション推進の必要性が指摘されていま\nす。このような要請に応えるため、日米ＥＵ医薬品規制調和国際会議（ICH）が組織\nされ、品質、安全性及び有効性を含む各分野で、ハーモナイゼーションの促進を図る\nための活動が行われているところです。   \n\n今般、ICHの合意に基づき、別添のとおり「ICHQ4Bガイドライン」（以下「本ガ\nイドライン」という。）がとりまとめられましたので、下記について御了知の上、貴\n管下関係業者等に対して周知方御配慮願います。   \n\n記 \n\n１．本ガイドラインの目的 \n\n本ガイドラインは、Q4B 専門家作業部会（EWG）による薬局方テキスト"
}